wojas_bt/__init__.py
wojas_bt/main.py
wojas_bt-0.2.dist-info/METADATA
wojas_bt-0.2.dist-info/WHEEL
wojas_bt-0.2.dist-info/top_level.txt
wojas_bt-0.2.dist-info/RECORD
