Metadata-Version: 2.4
Name: wojas_bt
Version: 0.2
Summary: Easily create beautiful gradient and rainbow text in Python
Home-page: https://github.com/wojase/wojas_bt
Author: W0jas
License: MIT
Project-URL: Bug Tracker, https://github.com/wojase/wojas_bt/issues
Project-URL: Source, https://github.com/wojase/wojas_bt
Keywords: gradient rainbow text terminal colors ansi
Classifier: Development Status :: 4 - Beta
Classifier: Intended Audience :: Developers
Classifier: Topic :: Terminals
Classifier: Programming Language :: Python :: 3
Classifier: Programming Language :: Python :: 3.7
Classifier: Programming Language :: Python :: 3.8
Classifier: Programming Language :: Python :: 3.9
Classifier: Programming Language :: Python :: 3.10
Requires-Python: >=3.7
Dynamic: author
Dynamic: classifier
Dynamic: description
Dynamic: description-content-type
Dynamic: home-page
Dynamic: keywords
Dynamic: license
Dynamic: project-url
Dynamic: requires-python
Dynamic: summary
